dashkit_kiboui/ContributionGraph.py
dashkit_kiboui/ContributionGraphBlock.py
dashkit_kiboui/ContributionGraphCalendar.py
dashkit_kiboui/__init__.py
dashkit_kiboui/_imports_.py
dashkit_kiboui/dashkit_kiboui.js
dashkit_kiboui/dashkit_kiboui.js.LICENSE.txt
dashkit_kiboui/metadata.json
dashkit_kiboui/package-info.json
dashkit_kiboui/proptypes.js
dashkit_kiboui-1.1.1.dist-info/METADATA
dashkit_kiboui-1.1.1.dist-info/WHEEL
dashkit_kiboui-1.1.1.dist-info/licenses/LICENSE
dashkit_kiboui-1.1.1.dist-info/RECORD
