Metadata-Version: 2.4
Name: dashkit_kiboui
Version: 1.1.1
Summary: Contribution graph components for Dash with native theming support
Project-URL: Homepage, https://pypi.org/project/dashkit_kiboui/
Project-URL: Source, https://github.com/iamgp/dash_dashkit
Project-URL: Issues, https://github.com/iamgp/dash_dashkit/issues
License-File: LICENSE
Classifier: Framework :: Dash
Classifier: Intended Audience :: Developers
Classifier: License :: OSI Approved :: MIT License
Classifier: Programming Language :: Python :: 3
Classifier: Programming Language :: Python :: 3 :: Only
Classifier: Programming Language :: Python :: 3.10
Classifier: Programming Language :: Python :: 3.11
Classifier: Programming Language :: Python :: 3.12
Classifier: Topic :: Software Development :: User Interfaces
Requires-Python: >=3.8
Requires-Dist: dash>=2.0.0
